processgpt_agent_sdk/__init__.py
processgpt_agent_sdk/database.py
processgpt_agent_sdk/processgpt_agent_framework.py
processgpt_agent_sdk/single_run.py
processgpt_agent_sdk/utils.py
process_gpt_agent_sdk-0.4.10.dist-info/METADATA
process_gpt_agent_sdk-0.4.10.dist-info/WHEEL
process_gpt_agent_sdk-0.4.10.dist-info/top_level.txt
process_gpt_agent_sdk-0.4.10.dist-info/RECORD
