Metadata-Version: 2.4
Name: process-gpt-agent-sdk
Version: 0.4.10
Summary: Supabase 기반 이벤트/작업 폴링으로 A2A AgentExecutor를 실행하는 SDK
License: MIT
Project-URL: Homepage, https://github.com/your-org/process-gpt-agent-sdk
Project-URL: Issues, https://github.com/your-org/process-gpt-agent-sdk/issues
Keywords: agent,a2a,supabase,workflow,sdk,processgpt
Classifier: Programming Language :: Python :: 3
Classifier: Programming Language :: Python :: 3 :: Only
Classifier: License :: OSI Approved :: MIT License
Classifier: Operating System :: OS Independent
Requires-Python: >=3.9
Requires-Dist: supabase>=2.0.0
Requires-Dist: python-dotenv>=1.0.0
Requires-Dist: a2a-sdk==0.3.0
Requires-Dist: typing-extensions>=4.0.0
Requires-Dist: process-gpt-llm-factory==1.0.2
Requires-Dist: pydantic>=2.0.0
Requires-Dist: requests>=2.25.0
